genecover/__init__.py
genecover/api.py
genecover/correlation.py
genecover/solvers/__init__.py
genecover/solvers/greedy.py
genecover/solvers/gurobi.py
genecover/solvers/scip.py
genecover-0.1.0.dist-info/licenses/LICENSE.txt
genecover-0.1.0.dist-info/METADATA
genecover-0.1.0.dist-info/WHEEL
genecover-0.1.0.dist-info/top_level.txt
genecover-0.1.0.dist-info/RECORD
