Metadata-Version: 2.4
Name: genecover
Version: 0.1.0
Summary: A Combinatorial Approach for Label-free Marker Gene Selection
Home-page: https://github.com/danielchen05/GeneCover
Author: Daniel Chen
Author-email: xchen274@jh.edu
License: MIT
Project-URL: Documentation, https://github.com/danielchen05/GeneCover
Project-URL: Source, https://github.com/danielchen05/GeneCover
Platform: any
Classifier: Development Status :: 4 - Beta
Classifier: Programming Language :: Python
Requires-Python: >=3.8
License-File: LICENSE.txt
Requires-Dist: numpy
Requires-Dist: scipy
Requires-Dist: importlib-metadata; python_version < "3.8"
Provides-Extra: scip
Requires-Dist: pyscipopt; extra == "scip"
Provides-Extra: gurobi
Requires-Dist: gurobipy; extra == "gurobi"
Provides-Extra: all
Requires-Dist: pyscipopt; extra == "all"
Requires-Dist: gurobipy; extra == "all"
Provides-Extra: testing
Requires-Dist: setuptools; extra == "testing"
Requires-Dist: pytest; extra == "testing"
Requires-Dist: pytest-cov; extra == "testing"
Dynamic: license-file
